django_docker_helpers/__init__.py
django_docker_helpers/db.py
django_docker_helpers/files.py
django_docker_helpers/management.py
django_docker_helpers/utils.py
django_docker_helpers/cli/__init__.py
django_docker_helpers/cli/django/__init__.py
django_docker_helpers/cli/django/management/__init__.py
django_docker_helpers/cli/django/management/commands/__init__.py
django_docker_helpers/cli/django/management/commands/run_configured_uwsgi.py
django_docker_helpers/config/__init__.py
django_docker_helpers/config/exceptions.py
django_docker_helpers/config/backends/__init__.py
django_docker_helpers/config/backends/base.py
django_docker_helpers/config/backends/consul_parser.py
django_docker_helpers/config/backends/environment_parser.py
django_docker_helpers/config/backends/mpt_consul_parser.py
django_docker_helpers/config/backends/mpt_redis_parser.py
django_docker_helpers/config/backends/redis_parser.py
django_docker_helpers/config/backends/yaml_parser.py
django_docker_helpers-0.2.0.dist-info/METADATA
django_docker_helpers-0.2.0.dist-info/RECORD
django_docker_helpers-0.2.0.dist-info/WHEEL
django_docker_helpers-0.2.0.dist-info/top_level.txt
tests/__init__.py
tests/django_settings.py
tests/test_backend_base.py
tests/test_backend_consul.py
tests/test_backend_environment.py
tests/test_backend_mpt_consul.py
tests/test_backend_mpt_redis.py
tests/test_backend_redis.py
tests/test_backend_yaml.py
tests/test_cli.py
tests/test_config_loader.py
tests/test_management_helpers.py
tests/test_utils.py
tests/test_app/__init__.py
tests/test_app/models.py
tests/test_app/migrations/0001_initial.py
tests/test_app/migrations/__init__.py
