Metadata-Version: 2.1
Name: django-docker-helpers
Version: 0.2.0
Summary: Django Docker helpers
Home-page: https://github.com/night-crawler/django-docker-helpers
Author: night-crawler
Author-email: lilo.panic@gmail.com
License: MIT
Platform: UNKNOWN
Classifier: Environment :: Web Environment
Classifier: Intended Audience :: Developers
Classifier: Operating System :: OS Independent
Classifier: Programming Language :: Python
Classifier: Programming Language :: Python :: 3
Classifier: Programming Language :: Python :: 3.6
Classifier: Programming Language :: Python :: 3.7
Classifier: License :: OSI Approved :: MIT License
Requires-Dist: dpath
Requires-Dist: pyaml
Requires-Dist: gunicorn
Requires-Dist: django
Requires-Dist: terminaltables
